README.md
setup.py
gatzzt/__init__.py
gatzzt/pandas_helper.py
gatzzt.egg-info/PKG-INFO
gatzzt.egg-info/SOURCES.txt
gatzzt.egg-info/dependency_links.txt
gatzzt.egg-info/not-zip-safe
gatzzt.egg-info/top_level.txt