Metadata-Version: 1.0
Name: gatzzt
Version: 0.1
Summary: tools for data science
Home-page: http://github.com/GatzZ/gatzzt
Author: GatzZ
Author-email: instituteliew@gmail.com
License: MIT
Platform: UNKNOWN
